UniBotPluginsCaffold/__init__.py
UniBotPluginsCaffold/command.py
UniBotPluginsCaffold/create.py
UniBotPluginsCaffold/main.py
UniBotPluginsCaffold/types.py
UniBotPluginsCaffold/templates/__init__.py
UniBotPluginsCaffold/templates/main.py
UniBotPluginsCaffold/templates/manifestJson.py
UniBot_plugins_scaffold-0.0.2.dist-info/METADATA
UniBot_plugins_scaffold-0.0.2.dist-info/WHEEL
UniBot_plugins_scaffold-0.0.2.dist-info/entry_points.txt
UniBot_plugins_scaffold-0.0.2.dist-info/top_level.txt
UniBot_plugins_scaffold-0.0.2.dist-info/RECORD
